nonebot_plugin_daily_task/__init__.py
nonebot_plugin_daily_task/config.py
nonebot_plugin_daily_task-0.1.15.dist-info/LICENSE
nonebot_plugin_daily_task-0.1.15.dist-info/METADATA
nonebot_plugin_daily_task-0.1.15.dist-info/WHEEL
nonebot_plugin_daily_task-0.1.15.dist-info/top_level.txt
nonebot_plugin_daily_task-0.1.15.dist-info/RECORD
