Metadata-Version: 2.1
Name: nonebot_plugin_daily_task
Version: 0.1.15
Summary: 适用于NoneBot2的每日提醒小助手
Author-email: WMGray <1466787434@qq.com>
License: MIT
Requires-Python: <4.0,>=3.10
License-File: LICENSE
Requires-Dist: nonebot2 >=2.3.1
Requires-Dist: nonebot-plugin-apscheduler >=0.4.0
Requires-Dist: nonebot-plugin-localstore >=0.6.0
